ssiwebd/__init__.py
ssiwebd/ssiwebd.py
ssiwebd-0.0.3.dist-info/DESCRIPTION.rst
ssiwebd-0.0.3.dist-info/METADATA
ssiwebd-0.0.3.dist-info/RECORD
ssiwebd-0.0.3.dist-info/WHEEL
ssiwebd-0.0.3.dist-info/entry_points.txt
ssiwebd-0.0.3.dist-info/metadata.json
ssiwebd-0.0.3.dist-info/top_level.txt
