Metadata-Version: 2.0
Name: ssiwebd
Version: 0.0.3
Summary: Server Side Include Webd
Home-page: https://github.com/solomonhuang/ssiwebd
Author: Solomon Huang
Author-email: kaichan@gmail.com
License: BSD
Keywords: ssi webd
Platform: UNKNOWN
Classifier: Development Status :: 3 - Alpha
Classifier: Intended Audience :: Developers
Classifier: License :: OSI Approved :: BSD License
Classifier: Programming Language :: Python :: 2.7
Classifier: Programming Language :: Python :: 3.4
Classifier: Programming Language :: Python :: 3.5
